groundwork_web/__init__.py
groundwork_web/version.py
groundwork_web/applications/__init__.py
groundwork_web/applications/configuration.py
groundwork_web/applications/groundwork_web_app.py
groundwork_web/patterns/__init__.py
groundwork_web/patterns/gw_web_db_admin_pattern/__init__.py
groundwork_web/patterns/gw_web_db_admin_pattern/exceptions.py
groundwork_web/patterns/gw_web_db_admin_pattern/gw_web_db_admin_pattern.py
groundwork_web/patterns/gw_web_db_rest_pattern/__init__.py
groundwork_web/patterns/gw_web_db_rest_pattern/exceptions.py
groundwork_web/patterns/gw_web_db_rest_pattern/gw_web_db_rest_pattern.py
groundwork_web/patterns/gw_web_pattern/__init__.py
groundwork_web/patterns/gw_web_pattern/context.py
groundwork_web/patterns/gw_web_pattern/gw_web_pattern.py
groundwork_web/patterns/gw_web_pattern/menu.py
groundwork_web/patterns/gw_web_pattern/provider.py
groundwork_web/patterns/gw_web_pattern/route.py
groundwork_web/patterns/gw_web_pattern/server.py
groundwork_web/plugins/__init__.py
groundwork_web/plugins/gw_web/__init__.py
groundwork_web/plugins/gw_web/gw_web.py
groundwork_web/plugins/gw_web/templates/base.html
groundwork_web/plugins/gw_web/templates/macros.html
groundwork_web/plugins/gw_web/templates/master.html
groundwork_web/plugins/gw_web/templates/test.html
groundwork_web/plugins/gw_web_manager/__init__.py
groundwork_web/plugins/gw_web_manager/gw_web_manager.py
groundwork_web/plugins/gw_web_manager/templates/commands.html
groundwork_web/plugins/gw_web_manager/templates/contexts.html
groundwork_web/plugins/gw_web_manager/templates/documents.html
groundwork_web/plugins/gw_web_manager/templates/manager.html
groundwork_web/plugins/gw_web_manager/templates/menus.html
groundwork_web/plugins/gw_web_manager/templates/plugin_class_detail.html
groundwork_web/plugins/gw_web_manager/templates/plugin_detail.html
groundwork_web/plugins/gw_web_manager/templates/plugins.html
groundwork_web-0.1.3.dist-info/DESCRIPTION.rst
groundwork_web-0.1.3.dist-info/METADATA
groundwork_web-0.1.3.dist-info/RECORD
groundwork_web-0.1.3.dist-info/WHEEL
groundwork_web-0.1.3.dist-info/entry_points.txt
groundwork_web-0.1.3.dist-info/metadata.json
groundwork_web-0.1.3.dist-info/top_level.txt
