Metadata-Version: 2.0
Name: groundwork-web
Version: 0.1.3
Summary: Package for hosting groundwork apps and plugins like groundwork_web_app or groundwork_web_plugin.
Home-page: http://groundwork-web.readthedocs.org
Author: team useblocks
Author-email: info@useblocks.com
License: MIT license
Platform: any
Classifier: Development Status :: 4 - Beta
Classifier: Environment :: Console
Classifier: Environment :: Web Environment
Classifier: Environment :: Plugins
Classifier: Intended Audience :: Developers
Classifier: License :: OSI Approved :: MIT License
Classifier: Operating System :: OS Independent
Classifier: Programming Language :: Python
Classifier: Programming Language :: Python :: 2
Classifier: Programming Language :: Python :: 2.7
Classifier: Programming Language :: Python :: 3
Classifier: Programming Language :: Python :: 3.4
Classifier: Programming Language :: Python :: 3.5
Classifier: Programming Language :: Python :: 3.6
Requires-Dist: Flask (>0.10.1)
Requires-Dist: Flask-Admin
Requires-Dist: Flask-Babel
Requires-Dist: Flask-Restless
Requires-Dist: docutils
Requires-Dist: groundwork
Requires-Dist: groundwork-database
Requires-Dist: pytest-runner
Requires-Dist: sphinx
